docforge/__init__.py
docforge/__main__.py
docforge/main.py
docforge/cli/__init__.py
docforge/cli/interface.py
docforge/cli/rich_interface.py
docforge/cli/validation_ui.py
docforge/core/__init__.py
docforge/core/base.py
docforge/core/enhanced_processor.py
docforge/core/exceptions.py
docforge/core/performance.py
docforge/core/processor.py
docforge/core/validators.py
docforge/pdf/__init__.py
docforge/pdf/ocr.py
docforge/pdf/optimizer.py
docforge/pdf/pdf_merger.py
docforge/pdf/pdf_splitter.py
docforge/pdf/pdf_to_word.py
docforge/utils/__init__.py
docforge/utils/logger.py
docforge-0.1.0.dist-info/licenses/LICENSE
docforge-0.1.0.dist-info/METADATA
docforge-0.1.0.dist-info/WHEEL
docforge-0.1.0.dist-info/entry_points.txt
docforge-0.1.0.dist-info/top_level.txt
docforge-0.1.0.dist-info/RECORD
