Metadata-Version: 2.4
Name: docforge
Version: 0.1.0
Summary: Forge perfect documents from any format with precision, power, and simplicity
Author-email: Oscar Song <oscar2song@gmail.com>
Maintainer-email: Oscar Song <oscar2song@gmail.com>
License: MIT
Project-URL: Homepage, https://github.com/oscar2song/docforge
Project-URL: Documentation, https://oscar2song.github.io/docforge
Project-URL: Repository, https://github.com/oscar2song/docforge.git
Project-URL: Bug Tracker, https://github.com/oscar2song/docforge/issues
Project-URL: Changelog, https://github.com/oscar2song/docforge/blob/main/CHANGELOG.md
Keywords: pdf,ocr,document,processing,optimization
Classifier: Development Status :: 4 - Beta
Classifier: Intended Audience :: Developers
Classifier: Intended Audience :: End Users/Desktop
Classifier: License :: OSI Approved :: MIT License
Classifier: Operating System :: OS Independent
Classifier: Programming Language :: Python :: 3
Classifier: Programming Language :: Python :: 3.8
Classifier: Programming Language :: Python :: 3.9
Classifier: Programming Language :: Python :: 3.10
Classifier: Programming Language :: Python :: 3.11
Classifier: Topic :: Multimedia :: Graphics :: Graphics Conversion
Classifier: Topic :: Office/Business :: Office Suites
Classifier: Topic :: Text Processing :: Markup
Requires-Python: >=3.8
License-File: LICENSE
Requires-Dist: click>=8.0.0
Requires-Dist: Pillow>=9.0.0
Requires-Dist: PyPDF2>=3.0.0
Requires-Dist: pytesseract>=0.3.10
Requires-Dist: pdf2image>=1.16.0
Requires-Dist: tqdm>=4.64.0
Requires-Dist: pyyaml>=6.0
Requires-Dist: colorama>=0.4.4
Requires-Dist: rich>=12.0.0
Requires-Dist: reportlab>=3.6.0
Requires-Dist: PyMuPDF>=1.20.0
Requires-Dist: python-docx>=0.8.11
Provides-Extra: dev
Requires-Dist: pytest>=7.0.0; extra == "dev"
Requires-Dist: pytest-cov>=4.0.0; extra == "dev"
Requires-Dist: pytest-mock>=3.8.0; extra == "dev"
Requires-Dist: black>=22.0.0; extra == "dev"
Requires-Dist: flake8>=5.0.0; extra == "dev"
Requires-Dist: mypy>=0.991; extra == "dev"
Requires-Dist: pre-commit>=2.20.0; extra == "dev"
Requires-Dist: sphinx>=5.0.0; extra == "dev"
Requires-Dist: sphinx-rtd-theme>=1.0.0; extra == "dev"
Provides-Extra: web
Requires-Dist: fastapi>=0.85.0; extra == "web"
Requires-Dist: uvicorn>=0.18.0; extra == "web"
Requires-Dist: jinja2>=3.0.0; extra == "web"
Requires-Dist: python-multipart>=0.0.5; extra == "web"
Provides-Extra: all
Requires-Dist: docforge[dev,web]; extra == "all"
Dynamic: license-file
